taming_transformers_hugf/__init__.py
taming_transformers_hugf/main.py
taming_transformers_hugf/taming/lr_scheduler.py
taming_transformers_hugf/taming/util.py
taming_transformers_hugf/taming/data/ade20k.py
taming_transformers_hugf/taming/data/annotated_objects_coco.py
taming_transformers_hugf/taming/data/annotated_objects_dataset.py
taming_transformers_hugf/taming/data/annotated_objects_open_images.py
taming_transformers_hugf/taming/data/base.py
taming_transformers_hugf/taming/data/coco.py
taming_transformers_hugf/taming/data/custom.py
taming_transformers_hugf/taming/data/faceshq.py
taming_transformers_hugf/taming/data/helper_types.py
taming_transformers_hugf/taming/data/image_transforms.py
taming_transformers_hugf/taming/data/imagenet.py
taming_transformers_hugf/taming/data/open_images_helper.py
taming_transformers_hugf/taming/data/sflckr.py
taming_transformers_hugf/taming/data/utils.py
taming_transformers_hugf/taming/data/conditional_builder/objects_bbox.py
taming_transformers_hugf/taming/data/conditional_builder/objects_center_points.py
taming_transformers_hugf/taming/data/conditional_builder/utils.py
taming_transformers_hugf/taming/models/cond_transformer.py
taming_transformers_hugf/taming/models/dummy_cond_stage.py
taming_transformers_hugf/taming/models/vqgan.py
taming_transformers_hugf/taming/modules/util.py
taming_transformers_hugf/taming/modules/diffusionmodules/model.py
taming_transformers_hugf/taming/modules/discriminator/model.py
taming_transformers_hugf/taming/modules/losses/__init__.py
taming_transformers_hugf/taming/modules/losses/lpips.py
taming_transformers_hugf/taming/modules/losses/segmentation.py
taming_transformers_hugf/taming/modules/losses/vqperceptual.py
taming_transformers_hugf/taming/modules/misc/coord.py
taming_transformers_hugf/taming/modules/transformer/mingpt.py
taming_transformers_hugf/taming/modules/transformer/permuter.py
taming_transformers_hugf/taming/modules/vqvae/quantize.py
taming_transformers_hugf-0.0.1.dist-info/METADATA
taming_transformers_hugf-0.0.1.dist-info/WHEEL
taming_transformers_hugf-0.0.1.dist-info/licenses/LICENSE
taming_transformers_hugf-0.0.1.dist-info/RECORD
