Metadata-Version: 2.1
Name: taming_transformers_hugf
Version: 0.0.1
Summary: Taming Transformers for High-Resolution Image Synthesis, augmented with some utils of hugging-face
Project-URL: Homepage, https://github.com//flybywind/taming-transformers
Project-URL: Bug Tracker, https://github.com/flybywind/taming-transformers
Author-email: "tongxin.wen" <mail@tongx.in>
License-File: LICENSE
Classifier: License :: OSI Approved :: MIT License
Classifier: Operating System :: OS Independent
Classifier: Programming Language :: Python :: 3
Requires-Python: >=3.6
Requires-Dist: albumentations>=0.4.3
Requires-Dist: einops==0.3.0
Requires-Dist: huggingface-hub>=0.10.0
Requires-Dist: imageio-ffmpeg>=0.4.2
Requires-Dist: imageio>=2.9.0
Requires-Dist: more-itertools>=8.0.0
Requires-Dist: numpy
Requires-Dist: numpy>=1.19.2
Requires-Dist: omegaconf==2.0.0
Requires-Dist: opencv-python>=4.1.2.30
Requires-Dist: pudb>=2019.2
Requires-Dist: pytest>=7.2.1
Requires-Dist: pytorch-lightning>=1.0.8
Requires-Dist: streamlit>=0.73.1
Requires-Dist: test-tube>=0.7.5
Requires-Dist: torch>=1.7.0
Requires-Dist: torchvision>=0.8.1
Requires-Dist: tqdm
Requires-Dist: transformers>=4.3.1
